infromatica2datatfusion/__init__.py
infromatica2datatfusion/add.py
testaddmodule-0.0.1.dist-info/METADATA
testaddmodule-0.0.1.dist-info/WHEEL
testaddmodule-0.0.1.dist-info/top_level.txt
testaddmodule-0.0.1.dist-info/RECORD
