Metadata-Version: 2.1
Name: testaddmodule
Version: 0.0.1
Summary: My first Python package
Author: swagatikap111
Author-email: <swagatikap111@gmail.com>
Keywords: python,first package
Classifier: Development Status :: 3 - Alpha
Classifier: Intended Audience :: Education
Classifier: Programming Language :: Python :: 3
Classifier: Operating System :: Microsoft :: Windows
